{
  "AWSTemplateFormatVersion": "2010-09-09",
  "Description": "The AWS CloudFormation template for this Serverless application",
  "Resources": {
    "ServerlessDeploymentBucket": {
      "Type": "AWS::S3::Bucket",
      "Properties": {
        "BucketEncryption": {
          "ServerSideEncryptionConfiguration": [
            {
              "ServerSideEncryptionByDefault": {
                "SSEAlgorithm": "AES256"
              }
            }
          ]
        }
      }
    },
    "ServerlessDeploymentBucketPolicy": {
      "Type": "AWS::S3::BucketPolicy",
      "Properties": {
        "Bucket": {
          "Ref": "ServerlessDeploymentBucket"
        },
        "PolicyDocument": {
          "Statement": [
            {
              "Action": "s3:*",
              "Effect": "Deny",
              "Principal": "*",
              "Resource": [
                {
                  "Fn::Join": [
                    "",
                    [
                      "arn:",
                      {
                        "Ref": "AWS::Partition"
                      },
                      ":s3:::",
                      {
                        "Ref": "ServerlessDeploymentBucket"
                      },
                      "/*"
                    ]
                  ]
                },
                {
                  "Fn::Join": [
                    "",
                    [
                      "arn:",
                      {
                        "Ref": "AWS::Partition"
                      },
                      ":s3:::",
                      {
                        "Ref": "ServerlessDeploymentBucket"
                      }
                    ]
                  ]
                }
              ],
              "Condition": {
                "Bool": {
                  "aws:SecureTransport": false
                }
              }
            }
          ]
        }
      }
    },
    "SubmitScoreLogGroup": {
      "Type": "AWS::Logs::LogGroup",
      "Properties": {
        "LogGroupName": "/aws/lambda/leaderboard-dev-submitScore"
      }
    },
    "ListScoresLogGroup": {
      "Type": "AWS::Logs::LogGroup",
      "Properties": {
        "LogGroupName": "/aws/lambda/leaderboard-dev-listScores"
      }
    },
    "GetScoreLogGroup": {
      "Type": "AWS::Logs::LogGroup",
      "Properties": {
        "LogGroupName": "/aws/lambda/leaderboard-dev-getScore"
      }
    },
    "IamRoleLambdaExecution": {
      "Type": "AWS::IAM::Role",
      "Properties": {
        "AssumeRolePolicyDocument": {
          "Version": "2012-10-17",
          "Statement": [
            {
              "Effect": "Allow",
              "Principal": {
                "Service": [
                  "lambda.amazonaws.com"
                ]
              },
              "Action": [
                "sts:AssumeRole"
              ]
            }
          ]
        },
        "Policies": [
          {
            "PolicyName": {
              "Fn::Join": [
                "-",
                [
                  "leaderboard",
                  "dev",
                  "lambda"
                ]
              ]
            },
            "PolicyDocument": {
              "Version": "2012-10-17",
              "Statement": [
                {
                  "Effect": "Allow",
                  "Action": [
                    "logs:CreateLogStream",
                    "logs:CreateLogGroup"
                  ],
                  "Resource": [
                    {
                      "Fn::Sub": "arn:${AWS::Partition}:logs:${AWS::Region}:${AWS::AccountId}:log-group:/aws/lambda/leaderboard-dev*:*"
                    }
                  ]
                },
                {
                  "Effect": "Allow",
                  "Action": [
                    "logs:PutLogEvents"
                  ],
                  "Resource": [
                    {
                      "Fn::Sub": "arn:${AWS::Partition}:logs:${AWS::Region}:${AWS::AccountId}:log-group:/aws/lambda/leaderboard-dev*:*:*"
                    }
                  ]
                },
                {
                  "Effect": "Allow",
                  "Action": [
                    "dynamodb:Query",
                    "dynamodb:Scan",
                    "dynamodb:GetItem",
                    "dynamodb:PutItem"
                  ],
                  "Resource": "*"
                }
              ]
            }
          }
        ],
        "Path": "/",
        "RoleName": {
          "Fn::Join": [
            "-",
            [
              "leaderboard",
              "dev",
              {
                "Ref": "AWS::Region"
              },
              "lambdaRole"
            ]
          ]
        }
      }
    },
    "SubmitScoreLambdaFunction": {
      "Type": "AWS::Lambda::Function",
      "Properties": {
        "Code": {
          "S3Bucket": {
            "Ref": "ServerlessDeploymentBucket"
          },
          "S3Key": "serverless/leaderboard/dev/1612990616192-2021-02-10T20:56:56.192Z/leaderboard.zip"
        },
        "Handler": "leaderboard.submit",
        "Runtime": "nodejs12.x",
        "FunctionName": "leaderboard-dev-submitScore",
        "MemorySize": 128,
        "Timeout": 6,
        "Description": "Submit high score for player",
        "Environment": {
          "Variables": {
            "SCORE_TABLE": "leaderboard-dev"
          }
        },
        "Role": {
          "Fn::GetAtt": [
            "IamRoleLambdaExecution",
            "Arn"
          ]
        }
      },
      "DependsOn": [
        "SubmitScoreLogGroup"
      ]
    },
    "ListScoresLambdaFunction": {
      "Type": "AWS::Lambda::Function",
      "Properties": {
        "Code": {
          "S3Bucket": {
            "Ref": "ServerlessDeploymentBucket"
          },
          "S3Key": "serverless/leaderboard/dev/1612990616192-2021-02-10T20:56:56.192Z/leaderboard.zip"
        },
        "Handler": "leaderboard.list",
        "Runtime": "nodejs12.x",
        "FunctionName": "leaderboard-dev-listScores",
        "MemorySize": 128,
        "Timeout": 6,
        "Description": "List all scores",
        "Environment": {
          "Variables": {
            "SCORE_TABLE": "leaderboard-dev"
          }
        },
        "Role": {
          "Fn::GetAtt": [
            "IamRoleLambdaExecution",
            "Arn"
          ]
        }
      },
      "DependsOn": [
        "ListScoresLogGroup"
      ]
    },
    "GetScoreLambdaFunction": {
      "Type": "AWS::Lambda::Function",
      "Properties": {
        "Code": {
          "S3Bucket": {
            "Ref": "ServerlessDeploymentBucket"
          },
          "S3Key": "serverless/leaderboard/dev/1612990616192-2021-02-10T20:56:56.192Z/leaderboard.zip"
        },
        "Handler": "leaderboard.get",
        "Runtime": "nodejs12.x",
        "FunctionName": "leaderboard-dev-getScore",
        "MemorySize": 1024,
        "Timeout": 6,
        "Environment": {
          "Variables": {
            "SCORE_TABLE": "leaderboard-dev"
          }
        },
        "Role": {
          "Fn::GetAtt": [
            "IamRoleLambdaExecution",
            "Arn"
          ]
        }
      },
      "DependsOn": [
        "GetScoreLogGroup"
      ]
    },
    "SubmitScoreLambdaVersionR0ERD3bCVRnkEx1t0iDGRYLmUNzdMNkXDylU8AbAc": {
      "Type": "AWS::Lambda::Version",
      "DeletionPolicy": "Retain",
      "Properties": {
        "FunctionName": {
          "Ref": "SubmitScoreLambdaFunction"
        },
        "CodeSha256": "QweXyGJ2d4poJTnRZKu8aiav+qucKCpYzhEdaQXU9r0=",
        "Description": "Submit high score for player"
      }
    },
    "ListScoresLambdaVersion04XkcurJf8txUzR7jA0vzdvblVq2wFFErz9L2jdyU": {
      "Type": "AWS::Lambda::Version",
      "DeletionPolicy": "Retain",
      "Properties": {
        "FunctionName": {
          "Ref": "ListScoresLambdaFunction"
        },
        "CodeSha256": "QweXyGJ2d4poJTnRZKu8aiav+qucKCpYzhEdaQXU9r0=",
        "Description": "List all scores"
      }
    },
    "GetScoreLambdaVersiongAYenzLfrytDDlOdvlHrA0enheIdVPT7BY91uB5xDvE": {
      "Type": "AWS::Lambda::Version",
      "DeletionPolicy": "Retain",
      "Properties": {
        "FunctionName": {
          "Ref": "GetScoreLambdaFunction"
        },
        "CodeSha256": "QweXyGJ2d4poJTnRZKu8aiav+qucKCpYzhEdaQXU9r0="
      }
    },
    "ApiGatewayRestApi": {
      "Type": "AWS::ApiGateway::RestApi",
      "Properties": {
        "Name": "dev-leaderboard",
        "EndpointConfiguration": {
          "Types": [
            "EDGE"
          ]
        },
        "Policy": ""
      }
    },
    "ApiGatewayResourceScore": {
      "Type": "AWS::ApiGateway::Resource",
      "Properties": {
        "ParentId": {
          "Fn::GetAtt": [
            "ApiGatewayRestApi",
            "RootResourceId"
          ]
        },
        "PathPart": "score",
        "RestApiId": {
          "Ref": "ApiGatewayRestApi"
        }
      }
    },
    "ApiGatewayResourceScoreIdVar": {
      "Type": "AWS::ApiGateway::Resource",
      "Properties": {
        "ParentId": {
          "Ref": "ApiGatewayResourceScore"
        },
        "PathPart": "{id}",
        "RestApiId": {
          "Ref": "ApiGatewayRestApi"
        }
      }
    },
    "ApiGatewayMethodScorePost": {
      "Type": "AWS::ApiGateway::Method",
      "Properties": {
        "HttpMethod": "POST",
        "RequestParameters": {},
        "ResourceId": {
          "Ref": "ApiGatewayResourceScore"
        },
        "RestApiId": {
          "Ref": "ApiGatewayRestApi"
        },
        "ApiKeyRequired": false,
        "AuthorizationType": "NONE",
        "Integration": {
          "IntegrationHttpMethod": "POST",
          "Type": "AWS_PROXY",
          "Uri": {
            "Fn::Join": [
              "",
              [
                "arn:",
                {
                  "Ref": "AWS::Partition"
                },
                ":apigateway:",
                {
                  "Ref": "AWS::Region"
                },
                ":lambda:path/2015-03-31/functions/",
                {
                  "Fn::GetAtt": [
                    "SubmitScoreLambdaFunction",
                    "Arn"
                  ]
                },
                "/invocations"
              ]
            ]
          }
        },
        "MethodResponses": []
      }
    },
    "ApiGatewayMethodScoreGet": {
      "Type": "AWS::ApiGateway::Method",
      "Properties": {
        "HttpMethod": "GET",
        "RequestParameters": {},
        "ResourceId": {
          "Ref": "ApiGatewayResourceScore"
        },
        "RestApiId": {
          "Ref": "ApiGatewayRestApi"
        },
        "ApiKeyRequired": false,
        "AuthorizationType": "NONE",
        "Integration": {
          "IntegrationHttpMethod": "POST",
          "Type": "AWS_PROXY",
          "Uri": {
            "Fn::Join": [
              "",
              [
                "arn:",
                {
                  "Ref": "AWS::Partition"
                },
                ":apigateway:",
                {
                  "Ref": "AWS::Region"
                },
                ":lambda:path/2015-03-31/functions/",
                {
                  "Fn::GetAtt": [
                    "ListScoresLambdaFunction",
                    "Arn"
                  ]
                },
                "/invocations"
              ]
            ]
          }
        },
        "MethodResponses": []
      }
    },
    "ApiGatewayMethodScoreIdVarGet": {
      "Type": "AWS::ApiGateway::Method",
      "Properties": {
        "HttpMethod": "GET",
        "RequestParameters": {},
        "ResourceId": {
          "Ref": "ApiGatewayResourceScoreIdVar"
        },
        "RestApiId": {
          "Ref": "ApiGatewayRestApi"
        },
        "ApiKeyRequired": false,
        "AuthorizationType": "NONE",
        "Integration": {
          "IntegrationHttpMethod": "POST",
          "Type": "AWS_PROXY",
          "Uri": {
            "Fn::Join": [
              "",
              [
                "arn:",
                {
                  "Ref": "AWS::Partition"
                },
                ":apigateway:",
                {
                  "Ref": "AWS::Region"
                },
                ":lambda:path/2015-03-31/functions/",
                {
                  "Fn::GetAtt": [
                    "GetScoreLambdaFunction",
                    "Arn"
                  ]
                },
                "/invocations"
              ]
            ]
          }
        },
        "MethodResponses": []
      }
    },
    "ApiGatewayDeployment1612990613280": {
      "Type": "AWS::ApiGateway::Deployment",
      "Properties": {
        "RestApiId": {
          "Ref": "ApiGatewayRestApi"
        },
        "StageName": "dev"
      },
      "DependsOn": [
        "ApiGatewayMethodScorePost",
        "ApiGatewayMethodScoreGet",
        "ApiGatewayMethodScoreIdVarGet"
      ]
    },
    "SubmitScoreLambdaPermissionApiGateway": {
      "Type": "AWS::Lambda::Permission",
      "Properties": {
        "FunctionName": {
          "Fn::GetAtt": [
            "SubmitScoreLambdaFunction",
            "Arn"
          ]
        },
        "Action": "lambda:InvokeFunction",
        "Principal": "apigateway.amazonaws.com",
        "SourceArn": {
          "Fn::Join": [
            "",
            [
              "arn:",
              {
                "Ref": "AWS::Partition"
              },
              ":execute-api:",
              {
                "Ref": "AWS::Region"
              },
              ":",
              {
                "Ref": "AWS::AccountId"
              },
              ":",
              {
                "Ref": "ApiGatewayRestApi"
              },
              "/*/*"
            ]
          ]
        }
      }
    },
    "ListScoresLambdaPermissionApiGateway": {
      "Type": "AWS::Lambda::Permission",
      "Properties": {
        "FunctionName": {
          "Fn::GetAtt": [
            "ListScoresLambdaFunction",
            "Arn"
          ]
        },
        "Action": "lambda:InvokeFunction",
        "Principal": "apigateway.amazonaws.com",
        "SourceArn": {
          "Fn::Join": [
            "",
            [
              "arn:",
              {
                "Ref": "AWS::Partition"
              },
              ":execute-api:",
              {
                "Ref": "AWS::Region"
              },
              ":",
              {
                "Ref": "AWS::AccountId"
              },
              ":",
              {
                "Ref": "ApiGatewayRestApi"
              },
              "/*/*"
            ]
          ]
        }
      }
    },
    "GetScoreLambdaPermissionApiGateway": {
      "Type": "AWS::Lambda::Permission",
      "Properties": {
        "FunctionName": {
          "Fn::GetAtt": [
            "GetScoreLambdaFunction",
            "Arn"
          ]
        },
        "Action": "lambda:InvokeFunction",
        "Principal": "apigateway.amazonaws.com",
        "SourceArn": {
          "Fn::Join": [
            "",
            [
              "arn:",
              {
                "Ref": "AWS::Partition"
              },
              ":execute-api:",
              {
                "Ref": "AWS::Region"
              },
              ":",
              {
                "Ref": "AWS::AccountId"
              },
              ":",
              {
                "Ref": "ApiGatewayRestApi"
              },
              "/*/*"
            ]
          ]
        }
      }
    },
    "LeaderboardDynamoDbTable": {
      "Type": "AWS::DynamoDB::Table",
      "DeletionPolicy": "Retain",
      "Properties": {
        "AttributeDefinitions": [
          {
            "AttributeName": "id",
            "AttributeType": "S"
          }
        ],
        "KeySchema": [
          {
            "AttributeName": "id",
            "KeyType": "HASH"
          }
        ],
        "ProvisionedThroughput": {
          "ReadCapacityUnits": 1,
          "WriteCapacityUnits": 1
        },
        "StreamSpecification": {
          "StreamViewType": "NEW_AND_OLD_IMAGES"
        },
        "TableName": "leaderboard-dev"
      }
    }
  },
  "Outputs": {
    "ServerlessDeploymentBucketName": {
      "Value": {
        "Ref": "ServerlessDeploymentBucket"
      }
    },
    "SubmitScoreLambdaFunctionQualifiedArn": {
      "Description": "Current Lambda function version",
      "Value": {
        "Ref": "SubmitScoreLambdaVersionR0ERD3bCVRnkEx1t0iDGRYLmUNzdMNkXDylU8AbAc"
      }
    },
    "ListScoresLambdaFunctionQualifiedArn": {
      "Description": "Current Lambda function version",
      "Value": {
        "Ref": "ListScoresLambdaVersion04XkcurJf8txUzR7jA0vzdvblVq2wFFErz9L2jdyU"
      }
    },
    "GetScoreLambdaFunctionQualifiedArn": {
      "Description": "Current Lambda function version",
      "Value": {
        "Ref": "GetScoreLambdaVersiongAYenzLfrytDDlOdvlHrA0enheIdVPT7BY91uB5xDvE"
      }
    },
    "ServiceEndpoint": {
      "Description": "URL of the service endpoint",
      "Value": {
        "Fn::Join": [
          "",
          [
            "https://",
            {
              "Ref": "ApiGatewayRestApi"
            },
            ".execute-api.",
            {
              "Ref": "AWS::Region"
            },
            ".",
            {
              "Ref": "AWS::URLSuffix"
            },
            "/dev"
          ]
        ]
      }
    }
  }
}